[
  {
    "name": "Иван",
    "surname": "Иванов",
    "lastName": "Васильевич",
    "contacts": [
      {
        "type": "mobile",
        "value": "+7(754)524-36"
      },
      {
        "type": "email",
        "value": "ivanov@mail.ru"
      },
      {
        "type": "vk",
        "value": "vk.com/id1223"
      }
    ],
    "id": "1696961362756",
    "updatedAt": "2022-01-12T11:47:21.169Z",
    "createdAt": "2018-04-10T16:22:22.756Z"
  },
  {
    "name": "Ефор",
    "surname": "Пупаки",
    "lastName": "Угович",
    "contacts": [
      {
        "type": "email",
        "value": "pupaki@fdkl.ru"
      },
      {
        "type": "phone",
        "value": "+7(155)456-36-98"
      },
      {
        "type": "mobile",
        "value": "+7(654)896-52-52"
      },
      {
        "type": "tg",
        "value": "t.me/pupaki"
      }
    ],
    "id": "1696962240615",
    "updatedAt": "2021-01-01T11:05:34.680Z",
    "createdAt": "2020-02-11T12:12:00.615Z"
  },
  {
    "name": "Ильяс",
    "surname": "Попрыгайло",
    "lastName": "Банафатьевич",
    "contacts": [
      {
        "type": "email",
        "value": "ilas@mail.ru"
      },
      {
        "type": "phone",
        "value": "+7(126)555-45-66"
      },
      {
        "type": "tg",
        "value": "t.me/Poprygailo"
      }
    ],
    "id": "1696963988490",
    "updatedAt": "2021-01-11T17:00:28.099Z",
    "createdAt": "2020-05-05T11:13:04.490Z"
  },
  {
    "name": "Иван",
    "surname": "Побегайло",
    "lastName": "Максович",
    "contacts": [
      {
        "type": "phone",
        "value": "+7(159)874-12-35"
      },
      {
        "type": "email",
        "value": "pobegailo@sl.ee"
      },
      {
        "type": "mobile",
        "value": "+7(155)544-11-23"
      },
      {
        "type": "email",
        "value": "dfhbgxb@fdfsd.rr"
      },
      {
        "type": "tg",
        "value": "t.me/pobegailo"
      },
      {
        "type": "vk",
        "value": "vk.com/i122dfc"
      },
      {
        "type": "phone",
        "value": "+7(923)354-11-23"
      },
      {
        "type": "email",
        "value": "pobegailo@mail.ru"
      },
      {
        "type": "vk",
        "value": "vk.com/i1234"
      },
      {
        "type": "phone",
        "value": "+7(234)556-46-66"
      }
    ],
    "id": "1697742489634",
    "updatedAt": "2023-10-19T19:08:09.635Z",
    "createdAt": "2022-12-31T00:00:00.635Z"
  },
  {
    "name": "Петр",
    "surname": "Петров",
    "lastName": "Петрович",
    "contacts": [
      {
        "type": "phone",
        "value": "+7(125)544-44-23"
      },
      {
        "type": "mobile",
        "value": "+7(951)456-98-70"
      },
      {
        "type": "email",
        "value": "petrov@mail.ru"
      },
      {
        "type": "phone",
        "value": "+7(125)654-56-66"
      },
      {
        "type": "email",
        "value": "petrov@dgm.dj"
      }
    ],
    "id": "1697745372499",
    "updatedAt": "2023-10-25T08:39:50.338Z",
    "createdAt": "2022-12-10T12:00:00.499Z"
  },
  {
    "name": "Миртрудмай",
    "surname": "Длинопупенский",
    "lastName": "Великооктябрьский",
    "contacts": [
      {
        "type": "phone",
        "value": "+7(987)456-32-14"
      },
      {
        "type": "email",
        "value": "dlinopupenskii@dfk.rjg"
      },
      {
        "type": "vk",
        "value": "vk.com/dlinopupenskii"
      },
      {
        "type": "tg",
        "value": "t.me/dlinopupenskii"
      },
      {
        "type": "vk",
        "value": "vk.com/dlinopup"
      },
      {
        "type": "vk",
        "value": "vk.com/dlp"
      },
      {
        "type": "phone",
        "value": "+7(352)454-68-74"
      }
    ],
    "id": "1697817839644",
    "updatedAt": "2023-11-22T12:00:50.326Z",
    "createdAt": "2022-10-20T16:03:59.645Z"
  },
  {
    "name": "Ламаран",
    "surname": "Вашбалодь",
    "lastName": "Мухамед оглы",
    "contacts": [
      {
        "type": "phone",
        "value": "+7(654)123-36-98"
      },
      {
        "type": "email",
        "value": "vashbalod@mail.ru"
      },
      {
        "type": "tg",
        "value": "t.me/vashbalod"
      }
    ],
    "id": "1698129805238",
    "updatedAt": "2023-10-24T07:17:49.396Z",
    "createdAt": "2023-10-24T06:43:25.238Z"
  },
  {
    "name": "Ираклий",
    "surname": "Шлебизум",
    "lastName": "Банефатьевич",
    "contacts": [
      {
        "type": "phone",
        "value": "+7(654)488-92-56"
      },
      {
        "type": "email",
        "value": "shlebezum@ira.ru"
      }
    ],
    "id": "1698163052162",
    "updatedAt": "2023-10-24T15:57:32.210Z",
    "createdAt": "2023-10-24T15:57:32.210Z"
  },
  {
    "name": "Талиб",
    "surname": "Улыбака",
    "lastName": "Улан ме",
    "contacts": [
      {
        "type": "mobile",
        "value": "+7(957)898-65-23"
      },
      {
        "type": "tg",
        "value": "t.me/ulibaka"
      }
    ],
    "id": "1698163116564",
    "updatedAt": "2023-10-24T15:58:36.564Z",
    "createdAt": "2023-10-24T15:58:36.564Z"
  },
  {
    "name": "Асоль",
    "surname": "Всепропалова",
    "lastName": "Бенедиктовна",
    "contacts": [
      {
        "type": "phone",
        "value": "+7(315)865-49-29"
      },
      {
        "type": "email",
        "value": "vsepropalova@crid.ru"
      },
      {
        "type": "vk",
        "value": "vk.com/vsepropalova"
      },
      {
        "type": "tg",
        "value": "t.me/vsepropalova"
      }
    ],
    "id": "1698163196852",
    "updatedAt": "2023-11-22T11:59:53.498Z",
    "createdAt": "2023-10-24T15:59:56.852Z"
  },
  {
    "name": "Гляделка в окна",
    "surname": "Чикса бестыжая",
    "lastName": "",
    "contacts": [
      {
        "type": "email",
        "value": "chiksa_bestyzhaia@za.pochta"
      },
      {
        "type": "phone",
        "value": "+7(315)698-74-69"
      }
    ],
    "id": "1698163295232",
    "updatedAt": "2023-10-24T16:01:35.232Z",
    "createdAt": "2023-10-24T16:01:35.232Z"
  },
  {
    "name": "Петер",
    "surname": "Петеров",
    "lastName": "Петерович",
    "contacts": [
      {
        "type": "phone",
        "value": "+7(238)374-32-36"
      },
      {
        "type": "email",
        "value": "peterov@djd.ry"
      },
      {
        "type": "tg",
        "value": "t.me/peterov"
      }
    ],
    "id": "1700651423157",
    "updatedAt": "2023-11-22T11:10:23.175Z",
    "createdAt": "2023-11-22T11:10:23.175Z"
  },
  {
    "name": "Ильдар",
    "surname": "Лашаманов",
    "lastName": "Булгурович",
    "contacts": [
      {
        "type": "email",
        "value": "lashamanov@mil.ru"
      },
      {
        "type": "vk",
        "value": "vk.com/lashamanov"
      },
      {
        "type": "tg",
        "value": "t.me/lashamanov"
      },
      {
        "type": "phone",
        "value": "+7(985)357-45-66"
      },
      {
        "type": "phone",
        "value": "+7(636)545-42-63"
      }
    ],
    "id": "1700654208901",
    "updatedAt": "2023-11-22T11:57:10.097Z",
    "createdAt": "2023-11-22T11:56:48.901Z"
  }
]
